{
    "klass": "Specie",
    "id": 264,
    "dbSymbol": "siamwaff",
    "forms": [
        {
            "form": 0,
            "height": 0.5,
            "weight": 32.5,
            "type1": "steel",
            "type2": "__undef__",
            "baseHp": 80,
            "baseAtk": 150,
            "baseDfe": 80,
            "baseSpd": 85,
            "baseAts": 50,
            "baseDfs": 75,
            "evHp": 0,
            "evAtk": 3,
            "evDfe": 0,
            "evSpd": 0,
            "evAts": 0,
            "evDfs": 0,
            "evolutions": [],
            "experienceType": 1,
            "baseExperience": 147,
            "baseLoyalty": 70,
            "catchRate": 90,
            "femaleRate": 50,
            "breedGroups": [
                5,
                5
            ],
            "hatchSteps": 3840,
            "babyDbSymbol": "kanifien",
            "babyForm": 0,
            "itemHeld": [],
            "abilities": [
                "pickup",
                "gluttony",
                "quick_feet"
            ],
            "frontOffsetY": 31,
            "resources": {
                "icon": "siamwaff",
                "iconShiny": "siamwaff",
                "front": "siamwaff",
                "frontShiny": "siamwaff",
                "back": "siamwaff",
                "backShiny": "siamwaff",
                "footprint": "siamwaff",
                "character": "siamwaff",
                "characterShiny": "siamwaff",
                "cry": "264cry.ogg",
                "hasFemale": false
            },
            "moveSet": [
                {
                    "klass": "LevelLearnableMove",
                    "move": "play_rough",
                    "level": 1
                },
                {
                    "klass": "LevelLearnableMove",
                    "move": "rototiller",
                    "level": 1
                },
                {
                    "klass": "LevelLearnableMove",
                    "move": "switcheroo",
                    "level": 1
                },
                {
                    "klass": "LevelLearnableMove",
                    "move": "tackle",
                    "level": 1
                },
                {
                    "klass": "LevelLearnableMove",
                    "move": "growl",
                    "level": 1
                },
                {
                    "klass": "LevelLearnableMove",
                    "move": "tail_whip",
                    "level": 1
                },
                {
                    "klass": "LevelLearnableMove",
                    "move": "sand_attack",
                    "level": 1
                },
                {
                    "klass": "LevelLearnableMove",
                    "move": "tail_whip",
                    "level": 5
                },
                {
                    "klass": "LevelLearnableMove",
                    "move": "sand_attack",
                    "level": 7
                },
                {
                    "klass": "LevelLearnableMove",
                    "move": "headbutt",
                    "level": 11
                },
                {
                    "klass": "LevelLearnableMove",
                    "move": "odor_sleuth",
                    "level": 13
                },
                {
                    "klass": "LevelLearnableMove",
                    "move": "mud_sport",
                    "level": 17
                },
                {
                    "klass": "LevelLearnableMove",
                    "move": "fury_swipes",
                    "level": 19
                },
                {
                    "klass": "LevelLearnableMove",
                    "move": "covet",
                    "level": 24
                },
                {
                    "klass": "LevelLearnableMove",
                    "move": "bestow",
                    "level": 27
                },
                {
                    "klass": "LevelLearnableMove",
                    "move": "slash",
                    "level": 32
                },
                {
                    "klass": "LevelLearnableMove",
                    "move": "double_edge",
                    "level": 35
                },
                {
                    "klass": "LevelLearnableMove",
                    "move": "rest",
                    "level": 40
                },
                {
                    "klass": "LevelLearnableMove",
                    "move": "belly_drum",
                    "level": 43
                },
                {
                    "klass": "LevelLearnableMove",
                    "move": "fling",
                    "level": 48
                },
                {
                    "klass": "TutorLearnableMove",
                    "move": "super_fang"
                },
                {
                    "klass": "TutorLearnableMove",
                    "move": "snore"
                },
                {
                    "klass": "TutorLearnableMove",
                    "move": "icy_wind"
                },
                {
                    "klass": "TutorLearnableMove",
                    "move": "iron_tail"
                },
                {
                    "klass": "TutorLearnableMove",
                    "move": "helping_hand"
                },
                {
                    "klass": "TutorLearnableMove",
                    "move": "trick"
                },
                {
                    "klass": "TutorLearnableMove",
                    "move": "hyper_voice"
                },
                {
                    "klass": "TutorLearnableMove",
                    "move": "covet"
                },
                {
                    "klass": "TutorLearnableMove",
                    "move": "shock_wave"
                },
                {
                    "klass": "TutorLearnableMove",
                    "move": "water_pulse"
                },
                {
                    "klass": "TutorLearnableMove",
                    "move": "last_resort"
                },
                {
                    "klass": "TutorLearnableMove",
                    "move": "seed_bomb"
                },
                {
                    "klass": "TutorLearnableMove",
                    "move": "gunk_shot"
                },
                {
                    "klass": "TechLearnableMove",
                    "move": "cut"
                },
                {
                    "klass": "TechLearnableMove",
                    "move": "roar"
                },
                {
                    "klass": "TechLearnableMove",
                    "move": "surf"
                },
                {
                    "klass": "TechLearnableMove",
                    "move": "ice_beam"
                },
                {
                    "klass": "TechLearnableMove",
                    "move": "blizzard"
                },
                {
                    "klass": "TechLearnableMove",
                    "move": "hyper_beam"
                },
                {
                    "klass": "TechLearnableMove",
                    "move": "strength"
                },
                {
                    "klass": "TechLearnableMove",
                    "move": "thunderbolt"
                },
                {
                    "klass": "TechLearnableMove",
                    "move": "thunder_wave"
                },
                {
                    "klass": "TechLearnableMove",
                    "move": "thunder"
                },
                {
                    "klass": "TechLearnableMove",
                    "move": "dig"
                },
                {
                    "klass": "TechLearnableMove",
                    "move": "toxic"
                },
                {
                    "klass": "TechLearnableMove",
                    "move": "double_team"
                },
                {
                    "klass": "TechLearnableMove",
                    "move": "rest"
                },
                {
                    "klass": "TechLearnableMove",
                    "move": "substitute"
                },
                {
                    "klass": "TechLearnableMove",
                    "move": "thief"
                },
                {
                    "klass": "TechLearnableMove",
                    "move": "protect"
                },
                {
                    "klass": "TechLearnableMove",
                    "move": "swagger"
                },
                {
                    "klass": "TechLearnableMove",
                    "move": "attract"
                },
                {
                    "klass": "TechLearnableMove",
                    "move": "sleep_talk"
                },
                {
                    "klass": "TechLearnableMove",
                    "move": "return"
                },
                {
                    "klass": "TechLearnableMove",
                    "move": "frustration"
                },
                {
                    "klass": "TechLearnableMove",
                    "move": "hidden_power"
                },
                {
                    "klass": "TechLearnableMove",
                    "move": "rain_dance"
                },
                {
                    "klass": "TechLearnableMove",
                    "move": "sunny_day"
                },
                {
                    "klass": "TechLearnableMove",
                    "move": "shadow_ball"
                },
                {
                    "klass": "TechLearnableMove",
                    "move": "rock_smash"
                },
                {
                    "klass": "TechLearnableMove",
                    "move": "facade"
                },
                {
                    "klass": "TechLearnableMove",
                    "move": "secret_power"
                },
                {
                    "klass": "TechLearnableMove",
                    "move": "fling"
                },
                {
                    "klass": "TechLearnableMove",
                    "move": "giga_impact"
                },
                {
                    "klass": "TechLearnableMove",
                    "move": "shadow_claw"
                },
                {
                    "klass": "TechLearnableMove",
                    "move": "grass_knot"
                },
                {
                    "klass": "TechLearnableMove",
                    "move": "charge_beam"
                },
                {
                    "klass": "TechLearnableMove",
                    "move": "hone_claws"
                },
                {
                    "klass": "TechLearnableMove",
                    "move": "round"
                },
                {
                    "klass": "TechLearnableMove",
                    "move": "echoed_voice"
                },
                {
                    "klass": "TechLearnableMove",
                    "move": "retaliate"
                },
                {
                    "klass": "TechLearnableMove",
                    "move": "confide"
                }
            ]
        }
    ]
}